libs
applications
config
settings
