Metadata-Version: 1.1
Name: django-zoneke-contrib
Version: 0.04
Summary: Django Contrib
Home-page: http://github.com/chenchiyuan/contrib
Author: chen chiyuan
Author-email: chenchiyuan03@gmail.com
License: BSD License
Keywords: p,y,t,h,o,n, ,d,j,a,n,g,o, ,c,o,n,t,r,i,b, ,u,t,i,l, ,w,e,i,x,i,n
Platform: UNKNOWN
Classifier: Development Status :: 3 - Alpha
Classifier: Intended Audience :: Developers
Classifier: Topic :: Software Development :: Libraries :: Python Modules
Classifier: Environment :: Web Environment
Classifier: Topic :: Internet
Classifier: Operating System :: OS Independent
Classifier: Programming Language :: Python
Classifier: Framework :: Django
